scuteegfe/__init__.py
scuteegfe/HOSA/__init__.py
scuteegfe/HOSA/conventional/__init__.py
scuteegfe/HOSA/conventional/bicoherence.py
scuteegfe/HOSA/conventional/bicoherencex.py
scuteegfe/HOSA/conventional/bispectrumd.py
scuteegfe/HOSA/conventional/bispectrumdx.py
scuteegfe/HOSA/conventional/bispectrumi.py
scuteegfe/HOSA/conventional/cum2est.py
scuteegfe/HOSA/conventional/cum2x.py
scuteegfe/HOSA/conventional/cum3est.py
scuteegfe/HOSA/conventional/cum3x.py
scuteegfe/HOSA/conventional/cum4est.py
scuteegfe/HOSA/conventional/cum4x.py
scuteegfe/HOSA/conventional/cumest.py
scuteegfe/HOSA/conventional/demo/__init__.py
scuteegfe/HOSA/tools/__init__.py
scuteegfe/HOSA/tools/tools.py
scuteegfe/features/__init__.py
scuteegfe/features/any_feature.py
scuteegfe/features/pdc_dtf.py
scuteegfe/mne_features_wrapper/__init__.py
scuteegfe/mne_features_wrapper/feature_wrapper.py
scuteegfe-0.0.5.dist-info/METADATA
scuteegfe-0.0.5.dist-info/WHEEL
scuteegfe-0.0.5.dist-info/top_level.txt
scuteegfe-0.0.5.dist-info/RECORD
