Metadata-Version: 2.4
Name: scuteegfe
Version: 0.0.5
Summary: EEG Signal Feature Exacting, a wrapper of mne_features
Author: bkxcyu
Author-email: bkxcyu@gmail.com
Requires-Dist: requests
Requires-Dist: importlib-metadata; python_version >= "3.10"
Requires-Dist: einops
Requires-Dist: mne_features
Requires-Dist: EMD-signal
Requires-Dist: scipy
Requires-Dist: PyWavelets
Requires-Dist: pyts
Requires-Dist: antropy
Requires-Dist: pyentrp
Requires-Dist: tftb
Requires-Dist: statsmodels
Requires-Dist: scipy
Requires-Dist: emd-signal
Requires-Dist: pyentrp
Requires-Dist: nolds
Requires-Dist: pactools
Requires-Dist: EntropyHub
Requires-Dist: pykalman
Requires-Dist: mne_connectivity
Requires-Dist: spkit>=0.0.9.6.8
Requires-Dist: fooof
Requires-Dist: nilearn
Requires-Dist: pybispectra
Dynamic: author
Dynamic: author-email
Dynamic: description-content-type
Dynamic: requires-dist
Dynamic: summary
